[{"level": 42186, "volume": 37.39, "label": "step1_max_buy"}, {"level": 42240, "volume": 55.44, "label": "step1_max_sell"}, {"level": 42150, "volume": 14, "label": "step1_avg_buy"}, {"level": 42235, "volume": 18, "label": "step1_avg_sell"}, {"level": 42000, "volume": 273.341, "label": "step2_max_buy"}, {"level": 42570, "volume": 179.7493, "label": "step2_max_sell"}, {"level": 42077, "volume": 43, "label": "step2_avg_buy"}, {"level": 42275, "volume": 37, "label": "step2_avg_sell"}, {"level": 42000, "volume": 832.647, "label": "step3_max_buy"}, {"level": 43000, "volume": 809.187, "label": "step3_max_sell"}, {"level": 42034, "volume": 103, "label": "step3_avg_buy"}, {"level": 42352, "volume": 99, "label": "step3_avg_sell"}]