[{"level": 42194, "volume": 23.719, "label": "step1_max_buy"}, {"level": 42274, "volume": 56.7734, "label": "step1_max_sell"}, {"level": 42188, "volume": 15, "label": "step1_avg_buy"}, {"level": 42261, "volume": 16, "label": "step1_avg_sell"}, {"level": 41780, "volume": 181.9268, "label": "step2_max_buy"}, {"level": 42700, "volume": 178.605, "label": "step2_max_sell"}, {"level": 42111, "volume": 38, "label": "step2_avg_buy"}, {"level": 42338, "volume": 37, "label": "step2_avg_sell"}, {"level": 41400, "volume": 801.527, "label": "step3_max_buy"}, {"level": 43000, "volume": 780.595, "label": "step3_max_sell"}, {"level": 42046, "volume": 96, "label": "step3_avg_buy"}, {"level": 42464, "volume": 97, "label": "step3_avg_sell"}]