[{"level": 43688, "volume": 27.85, "label": "step1_max_buy"}, {"level": 43756, "volume": 36.2017, "label": "step1_max_sell"}, {"level": 43649, "volume": 14, "label": "step1_avg_buy"}, {"level": 43742, "volume": 16, "label": "step1_avg_sell"}, {"level": 43600, "volume": 238.4919, "label": "step2_max_buy"}, {"level": 43920, "volume": 240.162, "label": "step2_max_sell"}, {"level": 43568, "volume": 54, "label": "step2_avg_buy"}, {"level": 43816, "volume": 44, "label": "step2_avg_sell"}, {"level": 42800, "volume": 813.135, "label": "step3_max_buy"}, {"level": 48000, "volume": 1098.368, "label": "step3_max_sell"}, {"level": 43412, "volume": 123, "label": "step3_avg_buy"}, {"level": 44186, "volume": 118, "label": "step3_avg_sell"}, {"level": 43075, "volume": 9178852397, "label": "liq12h_max_long"}, {"level": 45050, "volume": 5220882288, "label": "liq12h_max_sell"}, {"level": 42588, "volume": 1653035256, "label": "liq12h_avg_longs"}, {"level": 44538, "volume": 1660815439, "label": "liq12h_avg_shorts"}, {"level": 42975, "volume": 99053695, "label": "liq12h_max_value"}, {"level": 42950, "volume": 32359355961, "label": "liq1d_max_long"}, {"level": 44075, "volume": 24053121093, "label": "liq1d_max_sell"}, {"level": 42588, "volume": 9265345113, "label": "liq1d_avg_longs"}, {"level": 44600, "volume": 10180494926, "label": "liq1d_avg_shorts"}, {"level": 42975, "volume": 178120666, "label": "liq1d_max_value"}, {"level": 42450, "volume": 61945911400, "label": "liq3d_max_long"}, {"level": 44700, "volume": 58197658815, "label": "liq3d_max_sell"}, {"level": 41975, "volume": 24095543383, "label": "liq3d_avg_longs"}, {"level": 44888, "volume": 28490555671, "label": "liq3d_avg_shorts"}, {"level": 44800, "volume": 348437705, "label": "liq3d_max_value"}]