[{"level": 41649, "volume": 95.205, "label": "step1_max_buy"}, {"level": 41704, "volume": 27.268, "label": "step1_max_sell"}, {"level": 41644, "volume": 23, "label": "step1_avg_buy"}, {"level": 41793, "volume": 16, "label": "step1_avg_sell"}, {"level": 41500, "volume": 239.771, "label": "step2_max_buy"}, {"level": 42120, "volume": 178.0754, "label": "step2_max_sell"}, {"level": 41573, "volume": 45, "label": "step2_avg_buy"}, {"level": 41820, "volume": 32, "label": "step2_avg_sell"}, {"level": 36800, "volume": 1119.995, "label": "step3_max_buy"}, {"level": 43200, "volume": 633.887, "label": "step3_max_sell"}, {"level": 41396, "volume": 115, "label": "step3_avg_buy"}, {"level": 41900, "volume": 90, "label": "step3_avg_sell"}]