[{"level": 38750, "volume": 31.138, "label": "step1_max_buy"}, {"level": 38800, "volume": 52.488, "label": "step1_max_sell"}, {"level": 38723, "volume": 17, "label": "step1_avg_buy"}, {"level": 38830, "volume": 15, "label": "step1_avg_sell"}, {"level": 38370, "volume": 196.7718, "label": "step2_max_buy"}, {"level": 39000, "volume": 458.75, "label": "step2_max_sell"}, {"level": 38642, "volume": 43, "label": "step2_avg_buy"}, {"level": 38883, "volume": 62, "label": "step2_avg_sell"}, {"level": 38000, "volume": 1131.927, "label": "step3_max_buy"}, {"level": 39500, "volume": 1155.054, "label": "step3_max_sell"}, {"level": 38600, "volume": 127, "label": "step3_avg_buy"}, {"level": 38950, "volume": 131, "label": "step3_avg_sell"}, {"level": 38125, "volume": 11100591075, "label": "liq12h_max_long"}, {"level": 40125, "volume": 7555238489, "label": "liq12h_max_sell"}, {"level": 37800, "volume": 3100728563, "label": "liq12h_avg_longs"}, {"level": 39588, "volume": 2861531351, "label": "liq12h_avg_shorts"}, {"level": 38125, "volume": 119648478, "label": "liq12h_max_value"}, {"level": 38025, "volume": 26581084880, "label": "liq1d_max_long"}, {"level": 39250, "volume": 20401628973, "label": "liq1d_max_sell"}, {"level": 37612, "volume": 10521444405, "label": "liq1d_avg_longs"}, {"level": 39588, "volume": 9241478416, "label": "liq1d_avg_shorts"}, {"level": 38125, "volume": 169841191, "label": "liq1d_max_value"}, {"level": 37400, "volume": 42040741933, "label": "liq3d_max_long"}, {"level": 39050, "volume": 37413115881, "label": "liq3d_max_sell"}, {"level": 37425, "volume": 17846218044, "label": "liq3d_avg_longs"}, {"level": 39588, "volume": 12806942929, "label": "liq3d_avg_shorts"}, {"level": 39025, "volume": 294279242, "label": "liq3d_max_value"}]