[{"level": 41750, "volume": 24.49, "label": "step1_max_buy"}, {"level": 41795, "volume": 29.355, "label": "step1_max_sell"}, {"level": 41735, "volume": 15, "label": "step1_avg_buy"}, {"level": 41831, "volume": 16, "label": "step1_avg_sell"}, {"level": 41300, "volume": 317.807, "label": "step2_max_buy"}, {"level": 41900, "volume": 313.838, "label": "step2_max_sell"}, {"level": 41669, "volume": 60, "label": "step2_avg_buy"}, {"level": 41882, "volume": 49, "label": "step2_avg_sell"}, {"level": 41000, "volume": 1142.322, "label": "step3_max_buy"}, {"level": 41900, "volume": 1219.974, "label": "step3_max_sell"}, {"level": 41585, "volume": 145, "label": "step3_avg_buy"}, {"level": 41924, "volume": 126, "label": "step3_avg_sell"}, {"level": 41100, "volume": 11045643319, "label": "liq12h_max_long"}, {"level": 42550, "volume": 6178811501, "label": "liq12h_max_sell"}, {"level": 40712, "volume": 3480299543, "label": "liq12h_avg_longs"}, {"level": 42862, "volume": 2298100525, "label": "liq12h_avg_shorts"}, {"level": 41100, "volume": 109619080, "label": "liq12h_max_value"}, {"level": 41050, "volume": 36451401565, "label": "liq1d_max_long"}, {"level": 42975, "volume": 29469921679, "label": "liq1d_max_sell"}, {"level": 40475, "volume": 14420788799, "label": "liq1d_avg_longs"}, {"level": 42862, "volume": 12220651521, "label": "liq1d_avg_shorts"}, {"level": 41050, "volume": 213043580, "label": "liq1d_max_value"}, {"level": 38125, "volume": 42299457849, "label": "liq3d_max_long"}, {"level": 42200, "volume": 10996655439, "label": "liq3d_max_sell"}, {"level": 39488, "volume": 14012873890, "label": "liq3d_avg_longs"}, {"level": 42862, "volume": 4395627056, "label": "liq3d_avg_shorts"}, {"level": 42200, "volume": 228198193, "label": "liq3d_max_value"}]