[{"level": 43113, "volume": 29.743, "label": "step1_max_buy"}, {"level": 43150, "volume": 55.38, "label": "step1_max_sell"}, {"level": 43081, "volume": 14, "label": "step1_avg_buy"}, {"level": 43186, "volume": 17, "label": "step1_avg_sell"}, {"level": 42640, "volume": 180.0878, "label": "step2_max_buy"}, {"level": 43580, "volume": 322.528, "label": "step2_max_sell"}, {"level": 43023, "volume": 37, "label": "step2_avg_buy"}, {"level": 43276, "volume": 52, "label": "step2_avg_sell"}, {"level": 42300, "volume": 622.543, "label": "step3_max_buy"}, {"level": 43600, "volume": 990.678, "label": "step3_max_sell"}, {"level": 42954, "volume": 93, "label": "step3_avg_buy"}, {"level": 43370, "volume": 116, "label": "step3_avg_sell"}]