[{"level": 42007, "volume": 30.01, "label": "step1_max_buy"}, {"level": 42045, "volume": 26.5575, "label": "step1_max_sell"}, {"level": 41976, "volume": 14, "label": "step1_avg_buy"}, {"level": 42053, "volume": 13, "label": "step1_avg_sell"}, {"level": 41590, "volume": 181.9941, "label": "step2_max_buy"}, {"level": 42430, "volume": 176.7867, "label": "step2_max_sell"}, {"level": 41914, "volume": 38, "label": "step2_avg_buy"}, {"level": 42133, "volume": 35, "label": "step2_avg_sell"}, {"level": 38600, "volume": 840.754, "label": "step3_max_buy"}, {"level": 42800, "volume": 761.565, "label": "step3_max_sell"}, {"level": 41779, "volume": 99, "label": "step3_avg_buy"}, {"level": 42200, "volume": 95, "label": "step3_avg_sell"}]