[{"level": 42288, "volume": 82.88535068, "label": "step1_max_buy"}, {"level": 42350, "volume": 94.487, "label": "step1_max_sell"}, {"level": 42263, "volume": 22, "label": "step1_avg_buy"}, {"level": 42344, "volume": 23, "label": "step1_avg_sell"}, {"level": 41860, "volume": 179.7809, "label": "step2_max_buy"}, {"level": 42350, "volume": 185.973, "label": "step2_max_sell"}, {"level": 42181, "volume": 43, "label": "step2_avg_buy"}, {"level": 42374, "volume": 51, "label": "step2_avg_sell"}, {"level": 41600, "volume": 1244.839, "label": "step3_max_buy"}, {"level": 44500, "volume": 1331.712, "label": "step3_max_sell"}, {"level": 42018, "volume": 112, "label": "step3_avg_buy"}, {"level": 42749, "volume": 132, "label": "step3_avg_sell"}, {"level": 41775, "volume": 4953736398, "label": "liq12h_max_long"}, {"level": 43975, "volume": 4901324249, "label": "liq12h_max_sell"}, {"level": 41250, "volume": 1495284623, "label": "liq12h_avg_longs"}, {"level": 43288, "volume": 1607975019, "label": "liq12h_avg_shorts"}, {"level": 43875, "volume": 61839129, "label": "liq12h_max_value"}, {"level": 41550, "volume": 12077699343, "label": "liq1d_max_long"}, {"level": 42800, "volume": 10788742445, "label": "liq1d_max_sell"}, {"level": 41200, "volume": 5621241195, "label": "liq1d_avg_longs"}, {"level": 43412, "volume": 4393739647, "label": "liq1d_avg_shorts"}, {"level": 43875, "volume": 83305668, "label": "liq1d_max_value"}, {"level": 41100, "volume": 22156527786, "label": "liq3d_max_long"}, {"level": 43475, "volume": 55659303829, "label": "liq3d_max_sell"}, {"level": 40962, "volume": 7496464003, "label": "liq3d_avg_longs"}, {"level": 43650, "volume": 17538833016, "label": "liq3d_avg_shorts"}, {"level": 43475, "volume": 280023060, "label": "liq3d_max_value"}]