[{"level": 41690, "volume": 28.819, "label": "step1_max_buy"}, {"level": 41746, "volume": 39.065, "label": "step1_max_sell"}, {"level": 41654, "volume": 12, "label": "step1_avg_buy"}, {"level": 41759, "volume": 14, "label": "step1_avg_sell"}, {"level": 41270, "volume": 181.7618, "label": "step2_max_buy"}, {"level": 42000, "volume": 266.643, "label": "step2_max_sell"}, {"level": 41565, "volume": 34, "label": "step2_avg_buy"}, {"level": 41836, "volume": 45, "label": "step2_avg_sell"}, {"level": 41000, "volume": 1187.471, "label": "step3_max_buy"}, {"level": 42500, "volume": 1146.729, "label": "step3_max_sell"}, {"level": 41493, "volume": 117, "label": "step3_avg_buy"}, {"level": 41904, "volume": 125, "label": "step3_avg_sell"}, {"level": 40000, "volume": 11334361911, "label": "liq12h_max_long"}, {"level": 42225, "volume": 11926529482, "label": "liq12h_max_sell"}, {"level": 40150, "volume": 3238318643, "label": "liq12h_avg_longs"}, {"level": 42700, "volume": 4800725130, "label": "liq12h_avg_shorts"}, {"level": 42225, "volume": 161278090, "label": "liq12h_max_value"}, {"level": 39400, "volume": 28231673200, "label": "liq1d_max_long"}, {"level": 42200, "volume": 20763758355, "label": "liq1d_max_sell"}, {"level": 39838, "volume": 10075921624, "label": "liq1d_avg_longs"}, {"level": 42700, "volume": 6511084324, "label": "liq1d_avg_shorts"}, {"level": 40075, "volume": 212741401, "label": "liq1d_max_value"}, {"level": 38125, "volume": 49582743742, "label": "liq3d_max_long"}, {"level": 42200, "volume": 7115021569, "label": "liq3d_max_sell"}, {"level": 39438, "volume": 12649487332, "label": "liq3d_avg_longs"}, {"level": 42700, "volume": 2203253555, "label": "liq3d_avg_shorts"}, {"level": 40125, "volume": 270648650, "label": "liq3d_max_value"}]