[{"level": 41349, "volume": 29.563, "label": "step1_max_buy"}, {"level": 41440, "volume": 26.914, "label": "step1_max_sell"}, {"level": 41344, "volume": 11, "label": "step1_avg_buy"}, {"level": 41429, "volume": 13, "label": "step1_avg_sell"}, {"level": 41000, "volume": 260.505, "label": "step2_max_buy"}, {"level": 41810, "volume": 176.8833, "label": "step2_max_sell"}, {"level": 41252, "volume": 42, "label": "step2_avg_buy"}, {"level": 41498, "volume": 39, "label": "step2_avg_sell"}, {"level": 40500, "volume": 1159.054, "label": "step3_max_buy"}, {"level": 42200, "volume": 676.414, "label": "step3_max_sell"}, {"level": 41185, "volume": 116, "label": "step3_avg_buy"}, {"level": 41560, "volume": 105, "label": "step3_avg_sell"}, {"level": 41225, "volume": 4337855842, "label": "liq12h_max_long"}, {"level": 42575, "volume": 7052917726, "label": "liq12h_max_sell"}, {"level": 40375, "volume": 1075996800, "label": "liq12h_avg_longs"}, {"level": 43512, "volume": 1697423182, "label": "liq12h_avg_shorts"}, {"level": 41650, "volume": 106924482, "label": "liq12h_max_value"}, {"level": 40650, "volume": 15456631872, "label": "liq1d_max_long"}, {"level": 43600, "volume": 23980788041, "label": "liq1d_max_sell"}, {"level": 40325, "volume": 4572560529, "label": "liq1d_avg_longs"}, {"level": 43512, "volume": 7829755409, "label": "liq1d_avg_shorts"}, {"level": 42650, "volume": 150054551, "label": "liq1d_max_value"}, {"level": 40650, "volume": 5189419339, "label": "liq3d_max_long"}, {"level": 44475, "volume": 41582133078, "label": "liq3d_max_sell"}, {"level": 40325, "volume": 1474283657, "label": "liq3d_avg_longs"}, {"level": 43862, "volume": 13721682682, "label": "liq3d_avg_shorts"}, {"level": 42300, "volume": 287073644, "label": "liq3d_max_value"}]