[{"level": 41699, "volume": 23.8878, "label": "step1_max_buy"}, {"level": 41730, "volume": 71.881, "label": "step1_max_sell"}, {"level": 41675, "volume": 12, "label": "step1_avg_buy"}, {"level": 41768, "volume": 18, "label": "step1_avg_sell"}, {"level": 41500, "volume": 425.545, "label": "step2_max_buy"}, {"level": 41950, "volume": 234.589, "label": "step2_max_sell"}, {"level": 41583, "volume": 56, "label": "step2_avg_buy"}, {"level": 41836, "volume": 45, "label": "step2_avg_sell"}, {"level": 41000, "volume": 1111.718, "label": "step3_max_buy"}, {"level": 42500, "volume": 1153.035, "label": "step3_max_sell"}, {"level": 41522, "volume": 130, "label": "step3_avg_buy"}, {"level": 41921, "volume": 126, "label": "step3_avg_sell"}, {"level": 39950, "volume": 14165993989, "label": "liq12h_max_long"}, {"level": 42200, "volume": 10605995354, "label": "liq12h_max_sell"}, {"level": 40150, "volume": 4487784887, "label": "liq12h_avg_longs"}, {"level": 42700, "volume": 3152676161, "label": "liq12h_avg_shorts"}, {"level": 42200, "volume": 169579561, "label": "liq12h_max_value"}, {"level": 39325, "volume": 29270275840, "label": "liq1d_max_long"}, {"level": 42200, "volume": 10605995354, "label": "liq1d_max_sell"}, {"level": 39812, "volume": 9649197197, "label": "liq1d_avg_longs"}, {"level": 42700, "volume": 3164282810, "label": "liq1d_avg_shorts"}, {"level": 42200, "volume": 169579561, "label": "liq1d_max_value"}, {"level": 38125, "volume": 67735836067, "label": "liq3d_max_long"}, {"level": 42200, "volume": 3650647935, "label": "liq3d_max_sell"}, {"level": 39262, "volume": 13627282326, "label": "liq3d_avg_longs"}, {"level": 42700, "volume": 1076940873, "label": "liq3d_avg_shorts"}, {"level": 38125, "volume": 336438383, "label": "liq3d_max_value"}]