[{"level": 43880, "volume": 116.966, "label": "step1_max_buy"}, {"level": 43955, "volume": 34.5, "label": "step1_max_sell"}, {"level": 43851, "volume": 23, "label": "step1_avg_buy"}, {"level": 43954, "volume": 16, "label": "step1_avg_sell"}, {"level": 43880, "volume": 194.73, "label": "step2_max_buy"}, {"level": 44070, "volume": 466.4808, "label": "step2_max_sell"}, {"level": 43793, "volume": 47, "label": "step2_avg_buy"}, {"level": 44033, "volume": 58, "label": "step2_avg_sell"}, {"level": 43100, "volume": 916.869, "label": "step3_max_buy"}, {"level": 48000, "volume": 1113.542, "label": "step3_max_sell"}, {"level": 43648, "volume": 117, "label": "step3_avg_buy"}, {"level": 44375, "volume": 129, "label": "step3_avg_sell"}, {"level": 43075, "volume": 9630973630, "label": "liq12h_max_long"}, {"level": 43925, "volume": 4419176248, "label": "liq12h_max_sell"}, {"level": 42700, "volume": 1825900258, "label": "liq12h_avg_longs"}, {"level": 44775, "volume": 1452566182, "label": "liq12h_avg_shorts"}, {"level": 42975, "volume": 106488711, "label": "liq12h_max_value"}, {"level": 42950, "volume": 32552966615, "label": "liq1d_max_long"}, {"level": 43950, "volume": 23359971836, "label": "liq1d_max_sell"}, {"level": 42700, "volume": 8925474015, "label": "liq1d_avg_longs"}, {"level": 44775, "volume": 9321313720, "label": "liq1d_avg_shorts"}, {"level": 42975, "volume": 183490455, "label": "liq1d_max_value"}, {"level": 42450, "volume": 63242116754, "label": "liq3d_max_long"}, {"level": 44700, "volume": 59603081591, "label": "liq3d_max_sell"}, {"level": 42212, "volume": 23663543490, "label": "liq3d_avg_longs"}, {"level": 45000, "volume": 31459722321, "label": "liq3d_avg_shorts"}, {"level": 44700, "volume": 360813581, "label": "liq3d_max_value"}]