[{"level": 42525, "volume": 51.61, "label": "step1_max_buy"}, {"level": 42554, "volume": 21.741, "label": "step1_max_sell"}, {"level": 42478, "volume": 19, "label": "step1_avg_buy"}, {"level": 42563, "volume": 12, "label": "step1_avg_sell"}, {"level": 42110, "volume": 178.732, "label": "step2_max_buy"}, {"level": 42900, "volume": 396.784, "label": "step2_max_sell"}, {"level": 42438, "volume": 41, "label": "step2_avg_buy"}, {"level": 42654, "volume": 54, "label": "step2_avg_sell"}, {"level": 40700, "volume": 837.141, "label": "step3_max_buy"}, {"level": 44500, "volume": 1347.029, "label": "step3_max_sell"}, {"level": 42317, "volume": 102, "label": "step3_avg_buy"}, {"level": 42797, "volume": 134, "label": "step3_avg_sell"}, {"level": 41975, "volume": 4017839549, "label": "liq12h_max_long"}, {"level": 42875, "volume": 4104547390, "label": "liq12h_max_sell"}, {"level": 41362, "volume": 1114246101, "label": "liq12h_avg_longs"}, {"level": 43400, "volume": 1130696878, "label": "liq12h_avg_shorts"}, {"level": 41975, "volume": 46298389, "label": "liq12h_max_value"}, {"level": 41525, "volume": 14919820767, "label": "liq1d_max_long"}, {"level": 43650, "volume": 13291631572, "label": "liq1d_max_sell"}, {"level": 41312, "volume": 5318069291, "label": "liq1d_avg_longs"}, {"level": 43525, "volume": 4579453738, "label": "liq1d_avg_shorts"}, {"level": 42800, "volume": 88650690, "label": "liq1d_max_value"}, {"level": 41125, "volume": 23856055646, "label": "liq3d_max_long"}, {"level": 43475, "volume": 52685036602, "label": "liq3d_max_sell"}, {"level": 41075, "volume": 9525363821, "label": "liq3d_avg_longs"}, {"level": 43788, "volume": 20019537498, "label": "liq3d_avg_shorts"}, {"level": 43475, "volume": 288212311, "label": "liq3d_max_value"}]