[{"level": 43020, "volume": 30.389, "label": "step1_max_buy"}, {"level": 43201, "volume": 32.56779047, "label": "step1_max_sell"}, {"level": 43044, "volume": 12, "label": "step1_avg_buy"}, {"level": 43145, "volume": 17, "label": "step1_avg_sell"}, {"level": 42630, "volume": 175.9299, "label": "step2_max_buy"}, {"level": 43500, "volume": 332.362, "label": "step2_max_sell"}, {"level": 42993, "volume": 36, "label": "step2_avg_buy"}, {"level": 43213, "volume": 47, "label": "step2_avg_sell"}, {"level": 42600, "volume": 572.405, "label": "step3_max_buy"}, {"level": 43900, "volume": 1065.938, "label": "step3_max_sell"}, {"level": 42934, "volume": 91, "label": "step3_avg_buy"}, {"level": 43317, "volume": 121, "label": "step3_avg_sell"}]