[{"level": 41936, "volume": 29.2, "label": "step1_max_buy"}, {"level": 41973, "volume": 23.62, "label": "step1_max_sell"}, {"level": 41917, "volume": 15, "label": "step1_avg_buy"}, {"level": 41987, "volume": 11, "label": "step1_avg_sell"}, {"level": 41500, "volume": 231.036, "label": "step2_max_buy"}, {"level": 42370, "volume": 177.0356, "label": "step2_max_sell"}, {"level": 41836, "volume": 43, "label": "step2_avg_buy"}, {"level": 42022, "volume": 35, "label": "step2_avg_sell"}, {"level": 40200, "volume": 891.193, "label": "step3_max_buy"}, {"level": 43200, "volume": 686.314, "label": "step3_max_sell"}, {"level": 41755, "volume": 106, "label": "step3_avg_buy"}, {"level": 42109, "volume": 97, "label": "step3_avg_sell"}]