[{"level": 42574, "volume": 125.327, "label": "step1_max_buy"}, {"level": 42650, "volume": 23.645, "label": "step1_max_sell"}, {"level": 42565, "volume": 22, "label": "step1_avg_buy"}, {"level": 42660, "volume": 12, "label": "step1_avg_sell"}, {"level": 42530, "volume": 190.222, "label": "step2_max_buy"}, {"level": 43000, "volume": 254.607, "label": "step2_max_sell"}, {"level": 42509, "volume": 42, "label": "step2_avg_buy"}, {"level": 42751, "volume": 41, "label": "step2_avg_sell"}, {"level": 39700, "volume": 1714.364, "label": "step3_max_buy"}, {"level": 43000, "volume": 927.474, "label": "step3_max_sell"}, {"level": 42337, "volume": 130, "label": "step3_avg_buy"}, {"level": 42887, "volume": 104, "label": "step3_avg_sell"}, {"level": 40575, "volume": 8319683210, "label": "liq12h_max_long"}, {"level": 42650, "volume": 5775140673, "label": "liq12h_max_sell"}, {"level": 40912, "volume": 2098961439, "label": "liq12h_avg_longs"}, {"level": 43525, "volume": 1154577718, "label": "liq12h_avg_shorts"}, {"level": 41225, "volume": 111231585, "label": "liq12h_max_value"}, {"level": 40500, "volume": 17427595418, "label": "liq1d_max_long"}, {"level": 42625, "volume": 14885369993, "label": "liq1d_max_sell"}, {"level": 40838, "volume": 7219096441, "label": "liq1d_avg_longs"}, {"level": 43525, "volume": 2355378279, "label": "liq1d_avg_shorts"}, {"level": 40575, "volume": 134106764, "label": "liq1d_max_value"}, {"level": 42575, "volume": 52049650597, "label": "liq3d_max_long"}, {"level": 42650, "volume": 55720113775, "label": "liq3d_max_sell"}, {"level": 40688, "volume": 15407597493, "label": "liq3d_avg_longs"}, {"level": 44150, "volume": 17052487658, "label": "liq3d_avg_shorts"}, {"level": 42650, "volume": 373218584, "label": "liq3d_max_value"}]